[
  {
    "id": "1",
    "name": "Erik ten QUYET",
    "coachName": "Erik ten QUYET",
    "flag": "mu-flag.png",
    "coachImage": "coach-quyet.png"
  },
  {
    "id": "2",
    "name": "Carlo AncelotTUAN",
    "coachName": "Carlo AncelotTUAN",
    "flag": "real-mandrid-flag.png",
    "coachImage": "coach-tuan.png"
  },
  {
    "id": "3",
    "name": "XaVU Hernandez",
    "coachName": "XaVU Hernandez",
    "flag": "barca-flag.png",
    "coachImage": "coach-vu.png"
  },
  {
    "id": "4",
    "name": "Simone LAMzaghi",
    "coachName": "Simone LAMzaghi",
    "flag": "inter-flag.png",
    "coachImage": "coach-lam.png"
  },
  {
    "id": "5",
    "name": "Mikel ANHteta",
    "coachName": "Mikel ANHteta",
    "flag": "arsenal-flag.png",
    "coachImage": "coach-anh.png"
  },
  {
    "id": "6",
    "name": "Jürgen KLUU",
    "coachName": "Jürgen KLUU",
    "flag": "liver-flag.png",
    "coachImage": "coach-luu.png"
  }
]